maa_mcp/__init__.py
maa_mcp/__main__.py
maa_mcp/_version.py
maa_mcp/adb.py
maa_mcp/control.py
maa_mcp/core.py
maa_mcp/download.py
maa_mcp/main.py
maa_mcp/paths.py
maa_mcp/registry.py
maa_mcp/resource.py
maa_mcp/utils.py
maa_mcp/vision.py
maa_mcp/win32.py
maa_mcp-1.0.3.dist-info/METADATA
maa_mcp-1.0.3.dist-info/WHEEL
maa_mcp-1.0.3.dist-info/entry_points.txt
maa_mcp-1.0.3.dist-info/licenses/LICENSE
maa_mcp-1.0.3.dist-info/RECORD
