Metadata-Version: 2.4
Name: maa-mcp
Version: 1.0.3
Summary: MCP server based on MaaFramework, providing Android and Windows desktop automation capabilities for AI assistants
Project-URL: Homepage, https://github.com/MistEO/MaaMCP
Project-URL: Documentation, https://github.com/MistEO/MaaMCP#readme
Project-URL: Repository, https://github.com/MistEO/MaaMCP
Project-URL: Issues, https://github.com/MistEO/MaaMCP/issues
Author-email: MistEO <misteo@outlook.com>
License-Expression: AGPL-3.0-or-later
License-File: LICENSE
Keywords: adb,ai,android,automation,claude,cursor,maa,maaframework,mcp,ocr,windows
Classifier: Development Status :: 4 - Beta
Classifier: Environment :: Console
Classifier: Intended Audience :: Developers
Classifier: License :: OSI Approved :: GNU Affero General Public License v3 or later (AGPLv3+)
Classifier: Operating System :: OS Independent
Classifier: Programming Language :: Python :: 3
Classifier: Programming Language :: Python :: 3.10
Classifier: Programming Language :: Python :: 3.11
Classifier: Programming Language :: Python :: 3.12
Classifier: Programming Language :: Python :: 3.13
Classifier: Topic :: Software Development :: Libraries :: Python Modules
Classifier: Topic :: Software Development :: Testing
Classifier: Topic :: System :: Hardware
Requires-Python: >=3.10
Requires-Dist: fastmcp>=2.0.0
Requires-Dist: maafw>=5.2.6
Requires-Dist: opencv-python>=4.0.0
Requires-Dist: platformdirs>=4.0.0
